oneupsdk/__init__.py
oneupsdk/util.py
oneupsdk/version.py
oneupsdk/integration/__init__.py
oneupsdk/integration/api.py
oneupsdk/integration/exceptions.py
oneupsdk/integration/macros.py
oneupsdk/integration/util.py
oneupsdk-0.0.9.dist-info/LICENSE
oneupsdk-0.0.9.dist-info/METADATA
oneupsdk-0.0.9.dist-info/WHEEL
oneupsdk-0.0.9.dist-info/top_level.txt
oneupsdk-0.0.9.dist-info/RECORD
