Metadata-Version: 2.1
Name: oneupsdk
Version: 0.0.9
Summary: SDK Integration for the OneUp Learning platform.
Home-page: https://github.com/jlumbroso/oneup-sdk-python
Author: Jérémie Lumbroso
Author-email: lumbroso@cs.princeton.edu
License: LGPL-3.0-or-later
Platform: UNKNOWN
Classifier: License :: OSI Approved :: GNU Lesser General Public License v3 or later (LGPLv3+)
Classifier: Programming Language :: Python :: 3
Classifier: Programming Language :: Python :: 3.7
Requires-Dist: bs4
Requires-Dist: confuse
Requires-Dist: python-dateutil
Requires-Dist: PyYAML
Requires-Dist: requests
Requires-Dist: six
